[{"gender":"F","firstName":"Rebecca","lastName":"Burns","age":57,"phone":857186657},{"gender":"M","firstName":"Matt","lastName":"Bates","age":59,"phone":603363738},{"gender":"F","firstName":"Anya","lastName":"Francolini","age":63,"phone":572300518},{"gender":"M","firstName":"Scottie","lastName":"Goth","age":33,"phone":711710063},{"gender":"F","firstName":"Millie","lastName":"Graves","age":53,"phone":642864605},{"gender":"F","firstName":"Esther","lastName":"Burns","age":74,"phone":749885763},{"gender":"F","firstName":"Anna","lastName":"Bates","age":34,"phone":885515506},{"gender":"M","firstName":"Clyde","lastName":"Whelan","age":32,"phone":545486549},{"gender":"M","firstName":"Jake","lastName":"Hart","age":71,"phone":729075003},{"gender":"F","firstName":"Sophie","lastName":"Hart","age":64,"phone":714947320},{"gender":"F","firstName":"Marielle","lastName":"Fairfax","age":62,"phone":509805511},{"gender":"M","firstName":"Chris","lastName":"Taylor-Joy","age":54,"phone":750248156},{"gender":"M","firstName":"John","lastName":"Knightley","age":48,"phone":606287170},{"gender":"M","firstName":"Scottie","lastName":"Graves","age":76,"phone":524166742},{"gender":"M","firstName":"Matt","lastName":"Weston","age":26,"phone":631829139},{"gender":"M","firstName":"Chris","lastName":"Weston","age":48,"phone":803306706},{"gender":"F","firstName":"Sophie","lastName":"Hart","age":61,"phone":869808075},{"gender":"M","firstName":"Bill","lastName":"Woodhouse","age":45,"phone":774546877},{"gender":"F","firstName":"Gemma","lastName":"Weston","age":19,"phone":823896983},{"gender":"F","firstName":"Anya","lastName":"Smith","age":29,"phone":821343254}]